.gitignore
.project
.pydevproject
MANIFEST.in
README.rst
bootstrap.py
buildout.cfg
setup.py
collective/__init__.py
collective.js.fitvids.egg-info/PKG-INFO
collective.js.fitvids.egg-info/SOURCES.txt
collective.js.fitvids.egg-info/dependency_links.txt
collective.js.fitvids.egg-info/entry_points.txt
collective.js.fitvids.egg-info/namespace_packages.txt
collective.js.fitvids.egg-info/not-zip-safe
collective.js.fitvids.egg-info/requires.txt
collective.js.fitvids.egg-info/top_level.txt
collective/js/__init__.py
collective/js/fitvids/__init__.py
collective/js/fitvids/configure.zcml
collective/js/fitvids/profiles/default/jsregistry.xml
collective/js/fitvids/profiles/default/metadata.xml
collective/js/fitvids/resources/jquery.fitvids.js
collective/js/fitvids/upgrades/__init__.py
collective/js/fitvids/upgrades/configure.zcml
collective/js/fitvids/upgrades/v1x.py
docs/HISTORY.txt